{
    "seed": 372,
    "nodes_number": 5,
    "edge_prob": 0.1,
    "node_0": {
        "funca_num": 2,
        "funcb_num": 2,
        "funcc_num": 1,
        "funca_wl": 40,
        "funcb_wl": 5,
        "funcc_wl": 0,
        "node_type": "node_1",
        "neighbours": [
            "node_1",
            "node_4"
        ],
        "exp_history": [
            {
                "ram_usage": 0.36549399356189705,
                "cpu_usage": 0.19000000000000095,
                "functions": [
                    {
                        "name": "funca",
                        "service_count": 2,
                        "margin": 30,
                        "invoc_rate": 0,
                        "afet": 0.001,
                        "ram_xfunc": 0.02238979822361608,
                        "cpu_xfunc": 0,
                        "max_rate": 30,
                        "state": "Underload",
                        "prom_invoc_rate": 0
                    },
                    {
                        "name": "ocr",
                        "service_count": 1,
                        "margin": 1,
                        "invoc_rate": 0,
                        "afet": 0.001,
                        "ram_xfunc": 0.011290498349363335,
                        "cpu_xfunc": 0.020988727778273635,
                        "max_rate": 1,
                        "state": "Underload",
                        "prom_invoc_rate": 0
                    },
                    {
                        "name": "qrcode",
                        "service_count": 2,
                        "margin": 4,
                        "invoc_rate": 0,
                        "afet": 0.001,
                        "ram_xfunc": 0.005784895842509881,
                        "cpu_xfunc": 2.2944275991809477e-06,
                        "max_rate": 4,
                        "state": "Underload",
                        "prom_invoc_rate": 0
                    }
                ]
            },
            {
                "ram_usage": 0.36900375806149543,
                "cpu_usage": 0.22019599643642873,
                "functions": [
                    {
                        "name": "funca",
                        "service_count": 2,
                        "margin": 12,
                        "invoc_rate": 18,
                        "afet": 0.0011211307323943686,
                        "ram_xfunc": 0.022504321542325664,
                        "cpu_xfunc": 0.012268893746362284,
                        "max_rate": 30,
                        "state": "Underload",
                        "prom_invoc_rate": 6.454428101307249
                    },
                    {
                        "name": "ocr",
                        "service_count": 1,
                        "margin": 1,
                        "invoc_rate": 0,
                        "afet": 0.001,
                        "ram_xfunc": 0.011274184486299292,
                        "cpu_xfunc": 0.026177789178282843,
                        "max_rate": 1,
                        "state": "Underload",
                        "prom_invoc_rate": 0
                    },
                    {
                        "name": "qrcode",
                        "service_count": 2,
                        "margin": 3,
                        "invoc_rate": 1,
                        "afet": 0.023838136857142863,
                        "ram_xfunc": 0.005784895842509881,
                        "cpu_xfunc": 0,
                        "max_rate": 4,
                        "state": "Underload",
                        "prom_invoc_rate": 0.6363520663260668
                    }
                ]
            },
            {
                "ram_usage": 0.37274811591195467,
                "cpu_usage": 0.336351570028546,
                "functions": [
                    {
                        "name": "funca",
                        "service_count": 2,
                        "margin": 0,
                        "invoc_rate": 39,
                        "afet": 0.001018553629090906,
                        "ram_xfunc": 0.023152416942316574,
                        "cpu_xfunc": 0.010986196463869821,
                        "max_rate": 30,
                        "state": "Overload",
                        "prom_invoc_rate": 29.999454555371717
                    },
                    {
                        "name": "ocr",
                        "service_count": 1,
                        "margin": 1,
                        "invoc_rate": 0,
                        "afet": 0.001,
                        "ram_xfunc": 0.011276468427128256,
                        "cpu_xfunc": 0.025738499306874184,
                        "max_rate": 1,
                        "state": "Underload",
                        "prom_invoc_rate": 0
                    },
                    {
                        "name": "qrcode",
                        "service_count": 2,
                        "margin": 0,
                        "invoc_rate": 4,
                        "afet": 0.025728664163636377,
                        "ram_xfunc": 0.007090657442155935,
                        "cpu_xfunc": 0.08554238494287662,
                        "max_rate": 4,
                        "state": "Overload",
                        "prom_invoc_rate": 3.9999272740495626
                    }
                ]
            },
            {
                "ram_usage": 0.3749190016698871,
                "cpu_usage": 0.33909090909090867,
                "functions": [
                    {
                        "name": "funca",
                        "service_count": 2,
                        "margin": 0,
                        "invoc_rate": 39,
                        "afet": 0.001291772606666666,
                        "ram_xfunc": 0.023436463050078987,
                        "cpu_xfunc": 0.017082654170979858,
                        "max_rate": 30,
                        "state": "Overload",
                        "prom_invoc_rate": 29.99781834048433
                    },
                    {
                        "name": "ocr",
                        "service_count": 1,
                        "margin": 1,
                        "invoc_rate": 0,
                        "afet": 0.001,
                        "ram_xfunc": 0.011274837040821852,
                        "cpu_xfunc": 0.023706646013626657,
                        "max_rate": 1,
                        "state": "Underload",
                        "prom_invoc_rate": 0
                    },
                    {
                        "name": "qrcode",
                        "service_count": 2,
                        "margin": 0,
                        "invoc_rate": 4,
                        "afet": 0.025955321350000074,
                        "ram_xfunc": 0.007709115990913831,
                        "cpu_xfunc": 0.08180480108775622,
                        "max_rate": 4,
                        "state": "Overload",
                        "prom_invoc_rate": 3.999709112064577
                    }
                ]
            },
            {
                "ram_usage": 0.3766792674944974,
                "cpu_usage": 0.33837566589698187,
                "functions": [
                    {
                        "name": "funca",
                        "service_count": 2,
                        "margin": 0,
                        "invoc_rate": 39,
                        "afet": 0.001123454651303816,
                        "ram_xfunc": 0.023549031671377816,
                        "cpu_xfunc": 0.016618886455825908,
                        "max_rate": 30,
                        "state": "Overload",
                        "prom_invoc_rate": 29.980727973528236
                    },
                    {
                        "name": "ocr",
                        "service_count": 1,
                        "margin": 1,
                        "invoc_rate": 0,
                        "afet": 0.001,
                        "ram_xfunc": 0.012068995894779498,
                        "cpu_xfunc": 0.023021148792088168,
                        "max_rate": 1,
                        "state": "Underload",
                        "prom_invoc_rate": 0
                    },
                    {
                        "name": "qrcode",
                        "service_count": 2,
                        "margin": 0,
                        "invoc_rate": 4,
                        "afet": 0.02666837989999994,
                        "ram_xfunc": 0.007907818843033883,
                        "cpu_xfunc": 0.08572171928023538,
                        "max_rate": 4,
                        "state": "Overload",
                        "prom_invoc_rate": 3.999854550743609
                    }
                ]
            },
            {
                "ram_usage": 0.37791047473994077,
                "cpu_usage": 0.3385454545454568,
                "functions": [
                    {
                        "name": "funca",
                        "service_count": 2,
                        "margin": 0,
                        "invoc_rate": 39,
                        "afet": 0.0010988777260606119,
                        "ram_xfunc": 0.02358332044538151,
                        "cpu_xfunc": 0.01833843203362551,
                        "max_rate": 30,
                        "state": "Overload",
                        "prom_invoc_rate": 29.99727297518408
                    },
                    {
                        "name": "ocr",
                        "service_count": 1,
                        "margin": 1,
                        "invoc_rate": 0,
                        "afet": 0.001,
                        "ram_xfunc": 0.011274184486299292,
                        "cpu_xfunc": 0.02756047800405511,
                        "max_rate": 1,
                        "state": "Underload",
                        "prom_invoc_rate": 0
                    },
                    {
                        "name": "qrcode",
                        "service_count": 2,
                        "margin": 0,
                        "invoc_rate": 4,
                        "afet": 0.027246487322727237,
                        "ram_xfunc": 0.007990530128768583,
                        "cpu_xfunc": 0.08552311097237977,
                        "max_rate": 4,
                        "state": "Overload",
                        "prom_invoc_rate": 3.9996363966912103
                    }
                ]
            },
            {
                "ram_usage": 0.378493858483111,
                "cpu_usage": 0.38600000000000045,
                "functions": [
                    {
                        "name": "funca",
                        "service_count": 2,
                        "margin": 9,
                        "invoc_rate": 21,
                        "afet": 0.0014406525289575188,
                        "ram_xfunc": 0.02361743124996997,
                        "cpu_xfunc": 0,
                        "max_rate": 30,
                        "state": "Underload",
                        "prom_invoc_rate": 23.542886230593027
                    },
                    {
                        "name": "ocr",
                        "service_count": 1,
                        "margin": 1,
                        "invoc_rate": 0,
                        "afet": 0.001,
                        "ram_xfunc": 0.011566202635145673,
                        "cpu_xfunc": 0.029342147440598543,
                        "max_rate": 1,
                        "state": "Underload",
                        "prom_invoc_rate": 0
                    },
                    {
                        "name": "qrcode",
                        "service_count": 2,
                        "margin": 1,
                        "invoc_rate": 3,
                        "afet": 0.04163981866486493,
                        "ram_xfunc": 0.00807487280080969,
                        "cpu_xfunc": 0,
                        "max_rate": 4,
                        "state": "Underload",
                        "prom_invoc_rate": 3.3632694615132896
                    }
                ]
            }
        ]
    },
    "node_1": {
        "funca_num": 5,
        "funcb_num": 2,
        "funcc_num": 1,
        "funca_wl": 180,
        "funcb_wl": 0,
        "funcc_wl": 10,
        "node_type": "node_2",
        "neighbours": [
            "node_0",
            "node_2"
        ],
        "exp_history": [
            {
                "ram_usage": 0.1901919041261253,
                "cpu_usage": 0.2013781567607863,
                "functions": [
                    {
                        "name": "funca",
                        "service_count": 5,
                        "margin": 100,
                        "invoc_rate": 0,
                        "afet": 0,
                        "ram_xfunc": 0.018192111308286067,
                        "cpu_xfunc": 2.1612019093742253e-06,
                        "max_rate": 100,
                        "state": "Underload",
                        "prom_invoc_rate": 0
                    },
                    {
                        "name": "qrcode",
                        "service_count": 2,
                        "margin": 10,
                        "invoc_rate": 0,
                        "afet": 0,
                        "ram_xfunc": 0.0022446933489577714,
                        "cpu_xfunc": 0,
                        "max_rate": 10,
                        "state": "Underload",
                        "prom_invoc_rate": 0
                    },
                    {
                        "name": "ocr",
                        "service_count": 1,
                        "margin": 3,
                        "invoc_rate": 0,
                        "afet": 0,
                        "ram_xfunc": 0.002350346353808407,
                        "cpu_xfunc": 0.023121095427342635,
                        "max_rate": 3,
                        "state": "Underload",
                        "prom_invoc_rate": 0
                    }
                ]
            },
            {
                "ram_usage": 0.1994934924017261,
                "cpu_usage": 0.6447337321139617,
                "functions": [
                    {
                        "name": "funca",
                        "service_count": 5,
                        "margin": 0,
                        "invoc_rate": 174,
                        "afet": 0.0025665597104481755,
                        "ram_xfunc": 0.023530062362490264,
                        "cpu_xfunc": 0.06614038942868021,
                        "max_rate": 100,
                        "state": "Overload",
                        "prom_invoc_rate": 62.318422222222225
                    },
                    {
                        "name": "qrcode",
                        "service_count": 2,
                        "margin": 10,
                        "invoc_rate": 0,
                        "afet": 0,
                        "ram_xfunc": 0.0022446933489577714,
                        "cpu_xfunc": 0,
                        "max_rate": 10,
                        "state": "Underload",
                        "prom_invoc_rate": 0
                    },
                    {
                        "name": "ocr",
                        "service_count": 1,
                        "margin": 0,
                        "invoc_rate": 9,
                        "afet": 1.0368461245866933,
                        "ram_xfunc": 0.005894434450734389,
                        "cpu_xfunc": 0.5789905020062223,
                        "max_rate": 3,
                        "state": "Overload",
                        "prom_invoc_rate": 1.5692077683107326
                    }
                ]
            },
            {
                "ram_usage": 0.21035793687476267,
                "cpu_usage": 0.9186334048510858,
                "functions": [
                    {
                        "name": "ocr",
                        "service_count": 1,
                        "margin": 0,
                        "invoc_rate": 9,
                        "afet": 0.669363771662651,
                        "ram_xfunc": 0.009068208428253084,
                        "cpu_xfunc": 0.5107926298618243,
                        "max_rate": 3,
                        "state": "Overload",
                        "prom_invoc_rate": 3.0181818181818176
                    },
                    {
                        "name": "funca",
                        "service_count": 5,
                        "margin": 0,
                        "invoc_rate": 174,
                        "afet": 0.0024903351711122825,
                        "ram_xfunc": 0.03032251486352555,
                        "cpu_xfunc": 0.07285053621596689,
                        "max_rate": 100,
                        "state": "Overload",
                        "prom_invoc_rate": 100.2
                    },
                    {
                        "name": "qrcode",
                        "service_count": 2,
                        "margin": 10,
                        "invoc_rate": 0,
                        "afet": 0,
                        "ram_xfunc": 0.0022446933489577714,
                        "cpu_xfunc": 0,
                        "max_rate": 10,
                        "state": "Underload",
                        "prom_invoc_rate": 0
                    }
                ]
            },
            {
                "ram_usage": 0.2133503664781904,
                "cpu_usage": 0.7457550085445227,
                "functions": [
                    {
                        "name": "ocr",
                        "service_count": 1,
                        "margin": 0,
                        "invoc_rate": 9,
                        "afet": 0.36495516158433766,
                        "ram_xfunc": 0.008456379232609633,
                        "cpu_xfunc": 0.3337620532370114,
                        "max_rate": 3,
                        "state": "Overload",
                        "prom_invoc_rate": 3.0181269431464885
                    },
                    {
                        "name": "funca",
                        "service_count": 5,
                        "margin": 0,
                        "invoc_rate": 177,
                        "afet": 0.0019948450172664915,
                        "ram_xfunc": 0.03157820531242293,
                        "cpu_xfunc": 0.021285367512581428,
                        "max_rate": 100,
                        "state": "Overload",
                        "prom_invoc_rate": 100.0345448264577
                    },
                    {
                        "name": "qrcode",
                        "service_count": 2,
                        "margin": 10,
                        "invoc_rate": 0,
                        "afet": 0,
                        "ram_xfunc": 0.0022446933489577714,
                        "cpu_xfunc": 0,
                        "max_rate": 10,
                        "state": "Underload",
                        "prom_invoc_rate": 0
                    }
                ]
            },
            {
                "ram_usage": 0.21504444354269614,
                "cpu_usage": 0.641,
                "functions": [
                    {
                        "name": "funca",
                        "service_count": 5,
                        "margin": 0,
                        "invoc_rate": 177,
                        "afet": 0.002273199969354262,
                        "ram_xfunc": 0.03208365092145797,
                        "cpu_xfunc": 0.055348803122448935,
                        "max_rate": 100,
                        "state": "Overload",
                        "prom_invoc_rate": 99.67272727272727
                    },
                    {
                        "name": "qrcode",
                        "service_count": 2,
                        "margin": 10,
                        "invoc_rate": 0,
                        "afet": 0,
                        "ram_xfunc": 0.0022446933489577714,
                        "cpu_xfunc": 0,
                        "max_rate": 10,
                        "state": "Underload",
                        "prom_invoc_rate": 0
                    },
                    {
                        "name": "ocr",
                        "service_count": 1,
                        "margin": 0,
                        "invoc_rate": 9,
                        "afet": 0.2549469623878787,
                        "ram_xfunc": 0.00783105380470934,
                        "cpu_xfunc": 0.34619862492541703,
                        "max_rate": 3,
                        "state": "Overload",
                        "prom_invoc_rate": 3
                    }
                ]
            },
            {
                "ram_usage": 0.21436730757874345,
                "cpu_usage": 0.6273636363636362,
                "functions": [
                    {
                        "name": "funca",
                        "service_count": 5,
                        "margin": 0,
                        "invoc_rate": 177,
                        "afet": 0.0017581650227396514,
                        "ram_xfunc": 0.032158378595447505,
                        "cpu_xfunc": 0.05357148854251892,
                        "max_rate": 100,
                        "state": "Overload",
                        "prom_invoc_rate": 99.94727176857761
                    },
                    {
                        "name": "qrcode",
                        "service_count": 2,
                        "margin": 10,
                        "invoc_rate": 0,
                        "afet": 0,
                        "ram_xfunc": 0.0022446933489577714,
                        "cpu_xfunc": 0,
                        "max_rate": 10,
                        "state": "Underload",
                        "prom_invoc_rate": 0
                    },
                    {
                        "name": "ocr",
                        "service_count": 1,
                        "margin": 0,
                        "invoc_rate": 9,
                        "afet": 0.25041233467878987,
                        "ram_xfunc": 0.00804717347058222,
                        "cpu_xfunc": 0.32541952036003624,
                        "max_rate": 3,
                        "state": "Overload",
                        "prom_invoc_rate": 3.0000545464462993
                    }
                ]
            },
            {
                "ram_usage": 0.2139440357435416,
                "cpu_usage": 0.33619388738386646,
                "functions": [
                    {
                        "name": "funca",
                        "service_count": 5,
                        "margin": 100,
                        "invoc_rate": 0,
                        "afet": 0.001893198435801302,
                        "ram_xfunc": 0.03221435171943049,
                        "cpu_xfunc": 0,
                        "max_rate": 100,
                        "state": "Underload",
                        "prom_invoc_rate": 38.8
                    },
                    {
                        "name": "qrcode",
                        "service_count": 2,
                        "margin": 10,
                        "invoc_rate": 0,
                        "afet": 0,
                        "ram_xfunc": 0.0022446933489577714,
                        "cpu_xfunc": 0,
                        "max_rate": 10,
                        "state": "Underload",
                        "prom_invoc_rate": 0
                    },
                    {
                        "name": "ocr",
                        "service_count": 1,
                        "margin": 3,
                        "invoc_rate": 0,
                        "afet": 0.26690674369014067,
                        "ram_xfunc": 0.007555303285981653,
                        "cpu_xfunc": 0.01754458668380582,
                        "max_rate": 3,
                        "state": "Underload",
                        "prom_invoc_rate": 1.2909090909090908
                    }
                ]
            }
        ]
    },
    "node_2": {
        "funca_num": 4,
        "funcb_num": 2,
        "funcc_num": 1,
        "funca_wl": 10,
        "funcb_wl": 32,
        "funcc_wl": 0,
        "node_type": "node_3",
        "neighbours": [
            "node_1",
            "node_3"
        ],
        "exp_history": [
            {
                "ram_usage": 0.14322528529752243,
                "cpu_usage": 0.0656648302696411,
                "functions": [
                    {
                        "name": "funca",
                        "service_count": 4,
                        "margin": 120,
                        "invoc_rate": 0,
                        "afet": 0,
                        "ram_xfunc": 0.010856341338937847,
                        "cpu_xfunc": 0,
                        "max_rate": 120,
                        "state": "Underload",
                        "prom_invoc_rate": 0
                    },
                    {
                        "name": "qrcode",
                        "service_count": 2,
                        "margin": 20,
                        "invoc_rate": 0,
                        "afet": 0,
                        "ram_xfunc": 0.0007193448065991041,
                        "cpu_xfunc": 0,
                        "max_rate": 20,
                        "state": "Underload",
                        "prom_invoc_rate": 0
                    },
                    {
                        "name": "ocr",
                        "service_count": 1,
                        "margin": 5,
                        "invoc_rate": 0,
                        "afet": 0,
                        "ram_xfunc": 0.0004735031502454486,
                        "cpu_xfunc": 0.005355652952593553,
                        "max_rate": 5,
                        "state": "Underload",
                        "prom_invoc_rate": 0
                    }
                ]
            },
            {
                "ram_usage": 0.14511503948207172,
                "cpu_usage": 0.1885761559301078,
                "functions": [
                    {
                        "name": "funca",
                        "service_count": 4,
                        "margin": 111,
                        "invoc_rate": 9,
                        "afet": 0.013523005883347403,
                        "ram_xfunc": 0.011710200629440743,
                        "cpu_xfunc": 0.003188180790815804,
                        "max_rate": 120,
                        "state": "Underload",
                        "prom_invoc_rate": 7.4111497183614965
                    },
                    {
                        "name": "qrcode",
                        "service_count": 2,
                        "margin": 0,
                        "invoc_rate": 30,
                        "afet": 0.07338863129458195,
                        "ram_xfunc": 0.0025651390307451115,
                        "cpu_xfunc": 0.12285042481602962,
                        "max_rate": 20,
                        "state": "Overload",
                        "prom_invoc_rate": 14.072299436722995
                    },
                    {
                        "name": "ocr",
                        "service_count": 1,
                        "margin": 5,
                        "invoc_rate": 0,
                        "afet": 0,
                        "ram_xfunc": 0.0005391264393720518,
                        "cpu_xfunc": 0.009206537053190932,
                        "max_rate": 5,
                        "state": "Underload",
                        "prom_invoc_rate": 0
                    }
                ]
            },
            {
                "ram_usage": 0.14879758698470702,
                "cpu_usage": 0.22290909090909028,
                "functions": [
                    {
                        "name": "funca",
                        "service_count": 4,
                        "margin": 111,
                        "invoc_rate": 9,
                        "afet": 0.016881468981785056,
                        "ram_xfunc": 0.01303059049822817,
                        "cpu_xfunc": 0.0017338075700762978,
                        "max_rate": 120,
                        "state": "Underload",
                        "prom_invoc_rate": 9.981999672721322
                    },
                    {
                        "name": "qrcode",
                        "service_count": 2,
                        "margin": 0,
                        "invoc_rate": 31,
                        "afet": 0.08010101441203284,
                        "ram_xfunc": 0.002960582132077734,
                        "cpu_xfunc": 0.12071730558220378,
                        "max_rate": 20,
                        "state": "Overload",
                        "prom_invoc_rate": 19.945817196676305
                    },
                    {
                        "name": "ocr",
                        "service_count": 1,
                        "margin": 5,
                        "invoc_rate": 0,
                        "afet": 0,
                        "ram_xfunc": 0.00046083709111285957,
                        "cpu_xfunc": 0.00634033016412185,
                        "max_rate": 5,
                        "state": "Underload",
                        "prom_invoc_rate": 0
                    }
                ]
            },
            {
                "ram_usage": 0.15234555760905866,
                "cpu_usage": 0.2370454545454539,
                "functions": [
                    {
                        "name": "funca",
                        "service_count": 4,
                        "margin": 111,
                        "invoc_rate": 9,
                        "afet": 0.006465851736842114,
                        "ram_xfunc": 0.014379907961426169,
                        "cpu_xfunc": 0.0035259232775988877,
                        "max_rate": 120,
                        "state": "Underload",
                        "prom_invoc_rate": 10.018363970254004
                    },
                    {
                        "name": "qrcode",
                        "service_count": 2,
                        "margin": 0,
                        "invoc_rate": 31,
                        "afet": 0.06180470922504566,
                        "ram_xfunc": 0.0031531389879425665,
                        "cpu_xfunc": 0.12733974064256712,
                        "max_rate": 20,
                        "state": "Overload",
                        "prom_invoc_rate": 20.03672794050801
                    },
                    {
                        "name": "ocr",
                        "service_count": 1,
                        "margin": 5,
                        "invoc_rate": 0,
                        "afet": 0,
                        "ram_xfunc": 0.000503366660355475,
                        "cpu_xfunc": 0.0056597793873970174,
                        "max_rate": 5,
                        "state": "Underload",
                        "prom_invoc_rate": 0
                    }
                ]
            },
            {
                "ram_usage": 0.15199489339436623,
                "cpu_usage": 0.23017835390796915,
                "functions": [
                    {
                        "name": "qrcode",
                        "service_count": 2,
                        "margin": 0,
                        "invoc_rate": 31,
                        "afet": 0.07597758437500055,
                        "ram_xfunc": 0.003166951543806985,
                        "cpu_xfunc": 0.13366975693193778,
                        "max_rate": 20,
                        "state": "Overload",
                        "prom_invoc_rate": 20.0738222084841
                    },
                    {
                        "name": "ocr",
                        "service_count": 1,
                        "margin": 5,
                        "invoc_rate": 0,
                        "afet": 0,
                        "ram_xfunc": 0.0005649499133794422,
                        "cpu_xfunc": 0.0030053476892338443,
                        "max_rate": 5,
                        "state": "Underload",
                        "prom_invoc_rate": 0
                    },
                    {
                        "name": "funca",
                        "service_count": 4,
                        "margin": 111,
                        "invoc_rate": 9,
                        "afet": 0.010534863336363668,
                        "ram_xfunc": 0.015101501092785097,
                        "cpu_xfunc": 0.003145820180274494,
                        "max_rate": 120,
                        "state": "Underload",
                        "prom_invoc_rate": 10.000545484299144
                    }
                ]
            },
            {
                "ram_usage": 0.15212259129225925,
                "cpu_usage": 0.23304545454545456,
                "functions": [
                    {
                        "name": "funca",
                        "service_count": 4,
                        "margin": 111,
                        "invoc_rate": 9,
                        "afet": 0.00644170430363628,
                        "ram_xfunc": 0.01556213469313603,
                        "cpu_xfunc": 0.0023869310006313454,
                        "max_rate": 120,
                        "state": "Underload",
                        "prom_invoc_rate": 10.000181821487665
                    },
                    {
                        "name": "qrcode",
                        "service_count": 2,
                        "margin": 0,
                        "invoc_rate": 31,
                        "afet": 0.0522404809999998,
                        "ram_xfunc": 0.0032211644606977645,
                        "cpu_xfunc": 0.1262102138356645,
                        "max_rate": 20,
                        "state": "Overload",
                        "prom_invoc_rate": 20.091274386807033
                    },
                    {
                        "name": "ocr",
                        "service_count": 1,
                        "margin": 5,
                        "invoc_rate": 0,
                        "afet": 0,
                        "ram_xfunc": 0.0005345950475272032,
                        "cpu_xfunc": 0.007175236584336542,
                        "max_rate": 5,
                        "state": "Underload",
                        "prom_invoc_rate": 0
                    }
                ]
            },
            {
                "ram_usage": 0.152867104431876,
                "cpu_usage": 0.11342521045071885,
                "functions": [
                    {
                        "name": "funca",
                        "service_count": 4,
                        "margin": 120,
                        "invoc_rate": 0,
                        "afet": 0.001481293705357307,
                        "ram_xfunc": 0.015946495654486213,
                        "cpu_xfunc": 0,
                        "max_rate": 120,
                        "state": "Underload",
                        "prom_invoc_rate": 2.0363266122434136
                    },
                    {
                        "name": "qrcode",
                        "service_count": 2,
                        "margin": 20,
                        "invoc_rate": 0,
                        "afet": 0.04564273563059628,
                        "ram_xfunc": 0.003053612152603301,
                        "cpu_xfunc": 0,
                        "max_rate": 20,
                        "state": "Underload",
                        "prom_invoc_rate": 4.87263867929674
                    },
                    {
                        "name": "ocr",
                        "service_count": 1,
                        "margin": 5,
                        "invoc_rate": 0,
                        "afet": 0,
                        "ram_xfunc": 0.00047601452403897907,
                        "cpu_xfunc": 0.0072386200299281705,
                        "max_rate": 5,
                        "state": "Underload",
                        "prom_invoc_rate": 0
                    }
                ]
            }
        ]
    },
    "node_3": {
        "funca_num": 2,
        "funcb_num": 2,
        "funcc_num": 1,
        "funca_wl": 20,
        "funcb_wl": 0,
        "funcc_wl": 8,
        "node_type": "node_1",
        "neighbours": [
            "node_2",
            "node_4"
        ],
        "exp_history": [
            {
                "ram_usage": 0.34921014800589134,
                "cpu_usage": 0.4949182742131961,
                "functions": [
                    {
                        "name": "qrcode",
                        "service_count": 2,
                        "margin": 4,
                        "invoc_rate": 0,
                        "afet": 0,
                        "ram_xfunc": 0.004134585454951225,
                        "cpu_xfunc": 0,
                        "max_rate": 4,
                        "state": "Underload",
                        "prom_invoc_rate": 0
                    },
                    {
                        "name": "funca",
                        "service_count": 2,
                        "margin": 30,
                        "invoc_rate": 0,
                        "afet": 0,
                        "ram_xfunc": 0.010493076722792882,
                        "cpu_xfunc": 7.88878549021773e-06,
                        "max_rate": 30,
                        "state": "Underload",
                        "prom_invoc_rate": 0
                    },
                    {
                        "name": "ocr",
                        "service_count": 1,
                        "margin": 1,
                        "invoc_rate": 0,
                        "afet": 0.001,
                        "ram_xfunc": 0.006323416462253962,
                        "cpu_xfunc": 0.05204624008448456,
                        "max_rate": 1,
                        "state": "Underload",
                        "prom_invoc_rate": 0
                    }
                ]
            },
            {
                "ram_usage": 0.3515740267638713,
                "cpu_usage": 0.6431233524225071,
                "functions": [
                    {
                        "name": "qrcode",
                        "service_count": 2,
                        "margin": 4,
                        "invoc_rate": 0,
                        "afet": 0,
                        "ram_xfunc": 0.004134585454951225,
                        "cpu_xfunc": 0,
                        "max_rate": 4,
                        "state": "Underload",
                        "prom_invoc_rate": 0
                    },
                    {
                        "name": "funca",
                        "service_count": 2,
                        "margin": 12,
                        "invoc_rate": 18,
                        "afet": 0.00451652054591932,
                        "ram_xfunc": 0.012548949746123663,
                        "cpu_xfunc": 0.025435635562116185,
                        "max_rate": 30,
                        "state": "Underload",
                        "prom_invoc_rate": 9.234977934215966
                    },
                    {
                        "name": "ocr",
                        "service_count": 1,
                        "margin": 0,
                        "invoc_rate": 6,
                        "afet": 0.8942397134545452,
                        "ram_xfunc": 0.011772899280167108,
                        "cpu_xfunc": 0.2693619402844503,
                        "max_rate": 1,
                        "state": "Overload",
                        "prom_invoc_rate": 0.2
                    }
                ]
            },
            {
                "ram_usage": 0.36211212974872076,
                "cpu_usage": 0.8289339732402565,
                "functions": [
                    {
                        "name": "ocr",
                        "service_count": 1,
                        "margin": 0,
                        "invoc_rate": 7,
                        "afet": 1.0329400231111114,
                        "ram_xfunc": 0.012912585753821197,
                        "cpu_xfunc": 0.27403488579358143,
                        "max_rate": 1,
                        "state": "Overload",
                        "prom_invoc_rate": 0.4909090909090909
                    },
                    {
                        "name": "qrcode",
                        "service_count": 2,
                        "margin": 4,
                        "invoc_rate": 0,
                        "afet": 0,
                        "ram_xfunc": 0.004134585454951225,
                        "cpu_xfunc": 0,
                        "max_rate": 4,
                        "state": "Underload",
                        "prom_invoc_rate": 0
                    },
                    {
                        "name": "funca",
                        "service_count": 2,
                        "margin": 11,
                        "invoc_rate": 19,
                        "afet": 0.006170508473157411,
                        "ram_xfunc": 0.018246774052225363,
                        "cpu_xfunc": 0.03165321880021837,
                        "max_rate": 30,
                        "state": "Underload",
                        "prom_invoc_rate": 19.98181818181818
                    }
                ]
            },
            {
                "ram_usage": 0.36099985056501427,
                "cpu_usage": 0.8349090909090902,
                "functions": [
                    {
                        "name": "funca",
                        "service_count": 2,
                        "margin": 11,
                        "invoc_rate": 19,
                        "afet": 0.004312933294813477,
                        "ram_xfunc": 0.01953570271134624,
                        "cpu_xfunc": 0.038830543737681446,
                        "max_rate": 30,
                        "state": "Underload",
                        "prom_invoc_rate": 19.980365064358956
                    },
                    {
                        "name": "ocr",
                        "service_count": 1,
                        "margin": 0,
                        "invoc_rate": 7,
                        "afet": 0.9434403868148149,
                        "ram_xfunc": 0.013198745742749126,
                        "cpu_xfunc": 0.3332244571563441,
                        "max_rate": 1,
                        "state": "Overload",
                        "prom_invoc_rate": 0.49087339102610716
                    },
                    {
                        "name": "qrcode",
                        "service_count": 2,
                        "margin": 4,
                        "invoc_rate": 0,
                        "afet": 0,
                        "ram_xfunc": 0.004134585454951225,
                        "cpu_xfunc": 0,
                        "max_rate": 4,
                        "state": "Underload",
                        "prom_invoc_rate": 0
                    }
                ]
            },
            {
                "ram_usage": 0.3681560897366878,
                "cpu_usage": 0.8556389883820295,
                "functions": [
                    {
                        "name": "qrcode",
                        "service_count": 2,
                        "margin": 4,
                        "invoc_rate": 0,
                        "afet": 0,
                        "ram_xfunc": 0.004134585454951225,
                        "cpu_xfunc": 0,
                        "max_rate": 4,
                        "state": "Underload",
                        "prom_invoc_rate": 0
                    },
                    {
                        "name": "funca",
                        "service_count": 2,
                        "margin": 11,
                        "invoc_rate": 19,
                        "afet": 0.004879828518181836,
                        "ram_xfunc": 0.01973373817815913,
                        "cpu_xfunc": 0.03551036372496291,
                        "max_rate": 30,
                        "state": "Underload",
                        "prom_invoc_rate": 19.99927275371805
                    },
                    {
                        "name": "ocr",
                        "service_count": 1,
                        "margin": 0,
                        "invoc_rate": 7,
                        "afet": 1.371864483074075,
                        "ram_xfunc": 0.013793208082018274,
                        "cpu_xfunc": 0.2707147572106575,
                        "max_rate": 1,
                        "state": "Overload",
                        "prom_invoc_rate": 0.47271008326969927
                    }
                ]
            },
            {
                "ram_usage": 0.36864713701491547,
                "cpu_usage": 0.8363636363636364,
                "functions": [
                    {
                        "name": "qrcode",
                        "service_count": 2,
                        "margin": 4,
                        "invoc_rate": 0,
                        "afet": 0,
                        "ram_xfunc": 0.004134585454951225,
                        "cpu_xfunc": 0,
                        "max_rate": 4,
                        "state": "Underload",
                        "prom_invoc_rate": 0
                    },
                    {
                        "name": "funca",
                        "service_count": 2,
                        "margin": 11,
                        "invoc_rate": 19,
                        "afet": 0.0047118734194722435,
                        "ram_xfunc": 0.02096479711575647,
                        "cpu_xfunc": 0.035911748970642414,
                        "max_rate": 30,
                        "state": "Underload",
                        "prom_invoc_rate": 19.98181818181818
                    },
                    {
                        "name": "ocr",
                        "service_count": 1,
                        "margin": 0,
                        "invoc_rate": 7,
                        "afet": 0.9227520255185175,
                        "ram_xfunc": 0.01315087197004846,
                        "cpu_xfunc": 0.3067308606551626,
                        "max_rate": 1,
                        "state": "Overload",
                        "prom_invoc_rate": 0.4909090909090909
                    }
                ]
            },
            {
                "ram_usage": 0.36997622743874303,
                "cpu_usage": 0.7036363636363634,
                "functions": [
                    {
                        "name": "funca",
                        "service_count": 2,
                        "margin": 29,
                        "invoc_rate": 1,
                        "afet": 0.006008078680412346,
                        "ram_xfunc": 0.021244646605835537,
                        "cpu_xfunc": 0,
                        "max_rate": 30,
                        "state": "Underload",
                        "prom_invoc_rate": 10.58143340242173
                    },
                    {
                        "name": "ocr",
                        "service_count": 1,
                        "margin": 0,
                        "invoc_rate": 1,
                        "afet": 1.297547834250002,
                        "ram_xfunc": 0.013215371052289846,
                        "cpu_xfunc": 0.051919686942185204,
                        "max_rate": 1,
                        "state": "Overload",
                        "prom_invoc_rate": 0.2908985127813534
                    },
                    {
                        "name": "qrcode",
                        "service_count": 2,
                        "margin": 4,
                        "invoc_rate": 0,
                        "afet": 0,
                        "ram_xfunc": 0.004134585454951225,
                        "cpu_xfunc": 0,
                        "max_rate": 4,
                        "state": "Underload",
                        "prom_invoc_rate": 0
                    }
                ]
            }
        ]
    },
    "node_4": {
        "funca_num": 5,
        "funcb_num": 2,
        "funcc_num": 1,
        "funca_wl": 160,
        "funcb_wl": 0,
        "funcc_wl": 0,
        "node_type": "node_2",
        "neighbours": [
            "node_0",
            "node_3"
        ],
        "exp_history": [
            {
                "ram_usage": 0.1909491252327089,
                "cpu_usage": 0.16213661073032415,
                "functions": [
                    {
                        "name": "funca",
                        "service_count": 5,
                        "margin": 100,
                        "invoc_rate": 0,
                        "afet": 0,
                        "ram_xfunc": 0.013880874876160822,
                        "cpu_xfunc": 0,
                        "max_rate": 100,
                        "state": "Underload",
                        "prom_invoc_rate": 0
                    },
                    {
                        "name": "ocr",
                        "service_count": 1,
                        "margin": 3,
                        "invoc_rate": 0,
                        "afet": 0,
                        "ram_xfunc": 0.0005026146850583723,
                        "cpu_xfunc": 0.018360885473847108,
                        "max_rate": 3,
                        "state": "Underload",
                        "prom_invoc_rate": 0
                    },
                    {
                        "name": "qrcode",
                        "service_count": 2,
                        "margin": 10,
                        "invoc_rate": 0,
                        "afet": 0,
                        "ram_xfunc": 0.0009184635925188765,
                        "cpu_xfunc": 0,
                        "max_rate": 10,
                        "state": "Underload",
                        "prom_invoc_rate": 0
                    }
                ]
            },
            {
                "ram_usage": 0.19259718014521887,
                "cpu_usage": 0.1642727272727278,
                "functions": [
                    {
                        "name": "funca",
                        "service_count": 5,
                        "margin": 40,
                        "invoc_rate": 60,
                        "afet": 0.0014165585239709825,
                        "ram_xfunc": 0.014062612890359398,
                        "cpu_xfunc": 0.008714877995782152,
                        "max_rate": 100,
                        "state": "Underload",
                        "prom_invoc_rate": 19.094521666666665
                    },
                    {
                        "name": "ocr",
                        "service_count": 1,
                        "margin": 3,
                        "invoc_rate": 0,
                        "afet": 0,
                        "ram_xfunc": 0.0005121820141471106,
                        "cpu_xfunc": 0.016198111880688978,
                        "max_rate": 3,
                        "state": "Underload",
                        "prom_invoc_rate": 0
                    },
                    {
                        "name": "qrcode",
                        "service_count": 2,
                        "margin": 10,
                        "invoc_rate": 0,
                        "afet": 0,
                        "ram_xfunc": 0.0009184635925188765,
                        "cpu_xfunc": 0,
                        "max_rate": 10,
                        "state": "Underload",
                        "prom_invoc_rate": 0
                    }
                ]
            },
            {
                "ram_usage": 0.20000130313620346,
                "cpu_usage": 0.32981818181818223,
                "functions": [
                    {
                        "name": "funca",
                        "service_count": 5,
                        "margin": 0,
                        "invoc_rate": 158,
                        "afet": 0.0013697042252317712,
                        "ram_xfunc": 0.01930627155388459,
                        "cpu_xfunc": 0.05696654713070176,
                        "max_rate": 100,
                        "state": "Overload",
                        "prom_invoc_rate": 100.01818181818182
                    },
                    {
                        "name": "ocr",
                        "service_count": 1,
                        "margin": 3,
                        "invoc_rate": 0,
                        "afet": 0,
                        "ram_xfunc": 0.0005434407876353158,
                        "cpu_xfunc": 0.020923035683441855,
                        "max_rate": 3,
                        "state": "Underload",
                        "prom_invoc_rate": 0
                    },
                    {
                        "name": "qrcode",
                        "service_count": 2,
                        "margin": 10,
                        "invoc_rate": 0,
                        "afet": 0,
                        "ram_xfunc": 0.0009184635925188765,
                        "cpu_xfunc": 0,
                        "max_rate": 10,
                        "state": "Underload",
                        "prom_invoc_rate": 0
                    }
                ]
            },
            {
                "ram_usage": 0.20301179519713486,
                "cpu_usage": 0.30944198985436056,
                "functions": [
                    {
                        "name": "funca",
                        "service_count": 5,
                        "margin": 0,
                        "invoc_rate": 158,
                        "afet": 0.001319890489179834,
                        "ram_xfunc": 0.019759091354466577,
                        "cpu_xfunc": 0.05369855477709714,
                        "max_rate": 100,
                        "state": "Overload",
                        "prom_invoc_rate": 99.98909011564479
                    },
                    {
                        "name": "ocr",
                        "service_count": 1,
                        "margin": 3,
                        "invoc_rate": 0,
                        "afet": 0,
                        "ram_xfunc": 0.0005322239190485192,
                        "cpu_xfunc": 0.018682032147831307,
                        "max_rate": 3,
                        "state": "Underload",
                        "prom_invoc_rate": 0
                    },
                    {
                        "name": "qrcode",
                        "service_count": 2,
                        "margin": 10,
                        "invoc_rate": 0,
                        "afet": 0,
                        "ram_xfunc": 0.0009184635925188765,
                        "cpu_xfunc": 0,
                        "max_rate": 10,
                        "state": "Underload",
                        "prom_invoc_rate": 0
                    }
                ]
            },
            {
                "ram_usage": 0.20544305146332298,
                "cpu_usage": 0.30071455844651696,
                "functions": [
                    {
                        "name": "funca",
                        "service_count": 5,
                        "margin": 0,
                        "invoc_rate": 158,
                        "afet": 0.0013000254465648812,
                        "ram_xfunc": 0.020147932801599776,
                        "cpu_xfunc": 0.02184413161421555,
                        "max_rate": 100,
                        "state": "Overload",
                        "prom_invoc_rate": 100.0345448264577
                    },
                    {
                        "name": "ocr",
                        "service_count": 1,
                        "margin": 3,
                        "invoc_rate": 0,
                        "afet": 0,
                        "ram_xfunc": 0.0007803146595564917,
                        "cpu_xfunc": 0.01705057182569824,
                        "max_rate": 3,
                        "state": "Underload",
                        "prom_invoc_rate": 0
                    },
                    {
                        "name": "qrcode",
                        "service_count": 2,
                        "margin": 10,
                        "invoc_rate": 0,
                        "afet": 0,
                        "ram_xfunc": 0.0009184635925188765,
                        "cpu_xfunc": 0,
                        "max_rate": 10,
                        "state": "Underload",
                        "prom_invoc_rate": 0
                    }
                ]
            },
            {
                "ram_usage": 0.2112848131187215,
                "cpu_usage": 0.31627272727272704,
                "functions": [
                    {
                        "name": "funca",
                        "service_count": 5,
                        "margin": 0,
                        "invoc_rate": 158,
                        "afet": 0.0014139213209674467,
                        "ram_xfunc": 0.02695100108902598,
                        "cpu_xfunc": 0.021260632428696538,
                        "max_rate": 100,
                        "state": "Overload",
                        "prom_invoc_rate": 99.9836360661103
                    },
                    {
                        "name": "ocr",
                        "service_count": 1,
                        "margin": 3,
                        "invoc_rate": 0,
                        "afet": 0,
                        "ram_xfunc": 0.0006590735064492046,
                        "cpu_xfunc": 0.019337697299264753,
                        "max_rate": 3,
                        "state": "Underload",
                        "prom_invoc_rate": 0
                    },
                    {
                        "name": "qrcode",
                        "service_count": 2,
                        "margin": 10,
                        "invoc_rate": 0,
                        "afet": 0,
                        "ram_xfunc": 0.0009184635925188765,
                        "cpu_xfunc": 0,
                        "max_rate": 10,
                        "state": "Underload",
                        "prom_invoc_rate": 0
                    }
                ]
            },
            {
                "ram_usage": 0.21866510026395936,
                "cpu_usage": 0.3345575534990264,
                "functions": [
                    {
                        "name": "qrcode",
                        "service_count": 2,
                        "margin": 10,
                        "invoc_rate": 0,
                        "afet": 0,
                        "ram_xfunc": 0.0009184635925188765,
                        "cpu_xfunc": 0,
                        "max_rate": 10,
                        "state": "Underload",
                        "prom_invoc_rate": 0
                    },
                    {
                        "name": "funca",
                        "service_count": 5,
                        "margin": 4,
                        "invoc_rate": 96,
                        "afet": 0.001728785457284112,
                        "ram_xfunc": 0.02777153427077763,
                        "cpu_xfunc": 0,
                        "max_rate": 100,
                        "state": "Underload",
                        "prom_invoc_rate": 80.87272727272726
                    },
                    {
                        "name": "ocr",
                        "service_count": 1,
                        "margin": 3,
                        "invoc_rate": 0,
                        "afet": 0,
                        "ram_xfunc": 0.0006656716644414377,
                        "cpu_xfunc": 0.024262820260022917,
                        "max_rate": 3,
                        "state": "Underload",
                        "prom_invoc_rate": 0
                    }
                ]
            }
        ]
    }
}